govee/__init__.py
govee/temp/__init__.py
govee/temp/advertisement.py
govee/temp/const.py
govee/temp/scanner.py
govee/temp/util.py
govee-0.1.3.dist-info/WHEEL
govee-0.1.3.dist-info/METADATA
govee-0.1.3.dist-info/RECORD
